animated_parse_tree/__init__.py
animated_parse_tree/__main__.py
animated_parse_tree/default_bundles.py
animated_parse_tree/exceptions.py
animated_parse_tree/lexer.py
animated_parse_tree/node.py
animated_parse_tree/operand_.py
animated_parse_tree/operator_.py
animated_parse_tree/parse_tree.py
animated_parse_tree/parser.py
animated_parse_tree/scene.py
animated_parse_tree/temp_node.py
animated_parse_tree/tokenizer.py
animated_parse_tree/tree.py
animated_parse_tree/utils/__init__.py
animated_parse_tree/utils/custom_functions.py
animated_parse_tree/utils/io_utils.py
animated_parse_tree/utils/list_utils.py
animated_parse_tree/utils/mode.py
animated_parse_tree/utils/priority.py
animated_parse_tree/utils/string_utils.py
animated_parse_tree/v1/__init__.py
animated_parse_tree/v1/__main__.py
animated_parse_tree/v1/node.py
animated_parse_tree/v1/operand.py
animated_parse_tree/v1/operator_.py
animated_parse_tree/v1/parse_tree.py
animated_parse_tree-0.0.12.dist-info/LICENSE
animated_parse_tree-0.0.12.dist-info/METADATA
animated_parse_tree-0.0.12.dist-info/WHEEL
animated_parse_tree-0.0.12.dist-info/top_level.txt
animated_parse_tree-0.0.12.dist-info/RECORD
