Metadata-Version: 2.1
Name: animated-parse-tree
Version: 0.0.12
Summary: A simple parse tree utility package, with animated evaluations and configurable tree displays
Home-page: https://github.com/ethanolx/Animated-Parse-Tree-py
Author: ethanolx
Author-email: imotekhx@gmail.com
License: UNKNOWN
Project-URL: Bug Tracker, https://github.com/ethanolx/Animated-Parse-Tree-py/issues
Platform: UNKNOWN
Classifier: Programming Language :: Python :: 3
Classifier: License :: OSI Approved :: MIT License
Classifier: Operating System :: OS Independent
Requires-Python: >=3.8
License-File: LICENSE
Requires-Dist: termcolor
Provides-Extra: dev
Requires-Dist: pytest ; extra == 'dev'
